mmnpz/__init__.py
mmnpz/py.typed
mmnpz/reading.py
mmnpz/version.py
mmnpz/writing.py
mmnpz-1.0.0.dist-info/LICENSE
mmnpz-1.0.0.dist-info/METADATA
mmnpz-1.0.0.dist-info/WHEEL
mmnpz-1.0.0.dist-info/top_level.txt
mmnpz-1.0.0.dist-info/RECORD
