Metadata-Version: 2.1
Name: mmnpz
Version: 1.0.0
Summary: Memory-mapped .npz files.
Author-email: Jan Schlüter <jan.schlueter@jku.at>
License: MIT License
Project-URL: Documentation, https://mmnpz.readthedocs.io/
Project-URL: Repository, https://github.com/f0k/mmnpz
Project-URL: Issues, https://github.com/f0k/mmnpz/issues
Project-URL: Changelog, https://github.com/f0k/mmnpz/blob/main/CHANGELOG.md
Classifier: Intended Audience :: Science/Research
Classifier: Development Status :: 5 - Production/Stable
Classifier: License :: OSI Approved :: MIT License
Classifier: Programming Language :: Python :: 3
Classifier: Typing :: Typed
Requires-Python: >=3.8
License-File: LICENSE
Requires-Dist: numpy>=1.20
Requires-Dist: typing_extensions>=4.6.0
Provides-Extra: dev
Requires-Dist: isort; extra == "dev"
Requires-Dist: black; extra == "dev"
Requires-Dist: ruff; extra == "dev"
Requires-Dist: mypy; extra == "dev"
Requires-Dist: pytest; extra == "dev"
Requires-Dist: pytest-cov; extra == "dev"
Requires-Dist: build; extra == "dev"
Provides-Extra: doc
Requires-Dist: Sphinx; extra == "doc"
Requires-Dist: furo; extra == "doc"
Requires-Dist: sphinx-copybutton; extra == "doc"
Requires-Dist: sphinx-autobuild; extra == "doc"
Requires-Dist: myst-parser; extra == "doc"
